setup.py
tools/buildbsp.py
vmflib/__init__.py
vmflib/brush.py
vmflib/tools.py
vmflib/types.py
vmflib/vmf.py
vmflib.egg-info/PKG-INFO
vmflib.egg-info/SOURCES.txt
vmflib.egg-info/dependency_links.txt
vmflib.egg-info/entry_points.txt
vmflib.egg-info/top_level.txt
vmflib/games/__init__.py
vmflib/games/source.py
vmflib/games/tf2.py