Metadata-Version: 1.1
Name: vmflib
Version: 0.1
Summary: A package for creating Valve Map Format (VMF) files for the Source engine
Home-page: http://github.com/BHSPitMonkey/vmflib
Author: Stephen Eisenhauer
Author-email: bhs2007@gmail.com
License: BSD
Keywords: vmf valve map format source engine
Platform: UNKNOWN
Classifier: Programming Language :: Python :: 3
Classifier: Development Status :: 3 - Alpha
Classifier: Environment :: Other Environment
Classifier: Intended Audience :: Developers
Classifier: License :: OSI Approved :: BSD License
Classifier: Operating System :: OS Independent
Classifier: Topic :: Software Development :: Libraries :: Python Modules
Classifier: Topic :: Games/Entertainment
